{
  "framer:Text": [
    "LOCAL/",
    "CONTACTEZ-MOI",
    "cestmoitia",
    "BASED IN Puna'auia,",
    "Tahiti",
    "Available ALL AROUNd",
    "worldwidE",
    "filmaker / graphiste",
    "+ motion designer",
    "01",
    "//Portfolio",
    "2013 - 2025",
    "02",
    "//a propos de moi",
    "Since 2000",
    "Mon CV",
    "03",
    "//Services",
    "Fast Delivery",
    "04",
    "//",
    "Since 2001",
    "JEUNE",
    "Créatif",
    "AMOUREUX",
    "DE",
    "L'AUDIOVISUEL:",
    "VOTRE",
    "IDEE,",
    "MA",
    "VISION.",
    "05",
    "//Experience",
    "EXPERIENCE",
    "EXOTIC GARDEN",
    "Stage d’un mois chez Exotic Garden : création de contenu audiovisuel en quasi-autonomie. Une expérience enrichissante et professionnalisante.",
    "Jiku production",
    "J’ai effectué deux stages durant ma licence au sein d’Exotic Garden, en totale autonomie tout en travaillant en harmonie avec l’équipe. Suite à ces expériences, j’ai intégré l’entreprise en 2023 en tant que CVD.",
    "Aremiti",
    "Mission de 3 mois en tant que community manager",
    "Freelance",
    "Depuis le lycée, j’évolue dans le milieu professionnel de l’audiovisuel à travers différents médiums. C’est avant tout un métier passion qui m’anime et me motive au quotidien.",
    "Un projet ?",
    "BASED PUNA'AUIA,",
    "TAHITI",
    "Filmaker / graphiste",
    "+ Motion designer",
    "Installé à Puna'auia, Tahiti, je suis un artiste digital. Mon but est de mettre ma passion pour l'image au service de projets qui ont du sens.",
    "Instagram",
    "FACEBOOK",
    "©2026",
    "Retour en haut"
  ],
  "framer:Time Component": [
    "14:29:07"
  ],
  "framer:Title": [
    "MON",
    "Portfolio",
    "AMEX",
    "SOCREDO",
    "EXOTIC GARDEN",
    "AREMITI",
    "BIGA RANX",
    "PROJET PERSO",
    "Moi, c’est Tia, un jeune créatif passionné par l’audiovisuel, avec plus de 7 ans d’expérience professionnelle en entreprise et en freelance.",
    "Services",
    "//",
    "competence"
  ],
  "framer:Body Text": [
    "Je crée, j’imagine et je construis dans le monde digital, là où tout devient possible.",
    "Curieux et motivé, je continue chaque jour à apprendre à travers de nouvelles expériences et de nouveaux projets.  Parfois un peu désordonné, mais toujours animé par la créativité et l’efficacité.",
    "J’allie créativité et technique pour donner vie vos projets !"
  ],
  "framer:Category": [
    "Publicite // aftermovie",
    "Aftermovie",
    "CREA VIDEO // COMMUNITY MANAGER",
    "CAPTATION VIDEO",
    "vidéo"
  ],
  "framer:Text 1": [
    "à",
    "propos",
    "de",
    "Captation Vidéo",
    "Photographie",
    "Montage Vidéo",
    "Graphisme",
    "Motion design"
  ],
  "framer:Text 2": [
    "MOi",
    "Maitrise de mon matériel, expertise du terrain",
    "Mariage, portrait, real estate, evenement... etc",
    "Documentaire, clip vidéo, Publicité ... etc",
    "Création visuels tout support",
    "maitrise d'after effect"
  ],
  "framer:Position": [
    "cadreur // monteur // motion designer",
    "cadreur // monteur // motion designer // graphiste",
    "community manager // graphiste",
    "photographe // cadreur // monteur // motion designer // graphiste"
  ],
  "framer:Year": [
    "2022",
    "2020 - 2024",
    "2024",
    "2018 - 2026"
  ],
  "framer:Content": [
    "Create a free website with Framer, the website builder loved by startups, designers and agencies."
  ]
}